{"file:///home/miloc/pygui/README.md":{"language":"Markdown","code":11,"comment":0,"blank":3},"file:///home/miloc/pygui/apps/About%20PythOS.py":{"language":"Python","code":12,"comment":0,"blank":6},"file:///home/miloc/pygui/lib/initialization.py":{"language":"Python","code":27,"comment":0,"blank":14},"file:///home/miloc/pygui/lib/server.py":{"language":"Python","code":130,"comment":0,"blank":29},"file:///home/miloc/pygui/lib/guiSDK.py":{"language":"Python","code":104,"comment":0,"blank":23},"file:///home/miloc/pygui/lib/baseuiapi.py":{"language":"Python","code":229,"comment":0,"blank":54},"file:///home/miloc/pygui/pygui.py":{"language":"Python","code":113,"comment":0,"blank":14}}